bscearth.utils3-2.0.1-py3.7-nspkg.pth
bscearth/utils/__init__.py
bscearth/utils/config_parser.py
bscearth/utils/date.py
bscearth/utils/log.py
bscearth/utils/path.py
bscearth.utils3-2.0.1.dist-info/LICENSE
bscearth.utils3-2.0.1.dist-info/METADATA
bscearth.utils3-2.0.1.dist-info/WHEEL
bscearth.utils3-2.0.1.dist-info/namespace_packages.txt
bscearth.utils3-2.0.1.dist-info/top_level.txt
bscearth.utils3-2.0.1.dist-info/RECORD
